[
  { 
    "id": "41",
    "documentType": "2",
    "documentTypeDescription": "DNI",
    "documentNumber": "74427810",
    "pointSale": "MSC_TELECOMUNICACIONES_ANCASH",
    "pointSaleCode": "San Miguel",
    "names": "Johan Guisseppi",
    "motherLastName": "Marroquín",
    "lastName": "Córdova",
    "phone": "930000000",
    "email": "johan@gmail.com",
    "status": "A",
    "statusDescription": "Activo",
    "registerDate": "21/08/2018",
    "unregisterDate": "12/12/19",
    "authentication": "string",
    "userRegistration": "e760001",
    "userModification": "e760001",
    "modificationDate": "12/05/2019",
    "employeeId": "DV23566",
    "records": [
      {
        "id": "41",
        "documentType": "2",
        "documentTypeDescription": "DNI",
        "documentNumber": "74427810",
        "pointSale": "MSC_TELECOMUNICACIONES_ANCASH",
        "pointSaleCode": "San Miguel",
        "names": "Johan Guisseppi",
        "motherLastName": "Marroquín",
        "lastName": "Córdova",
        "phone": "930000000",
        "email": "johan@gmail.com",
        "status": "A",
        "statusDescription": "Activo",
        "registerDate": "21/08/2018",
        "unregisterDate": "12/12/19",
        "authentication": "string",
        "userRegistration": "e760001",
        "userModification": "e760001",
        "modificationDate": "12/05/2019"
      },
      {
        "id": "41",
        "documentType": "2",
        "documentTypeDescription": "DNI",
        "documentNumber": "74427810",
        "pointSale": "MSC_TELECOMUNICACIONES_ANCASH",
        "pointSaleCode": "San Miguel",
        "names": "Johan Guisseppi",
        "motherLastName": "Marroquín",
        "lastName": "Córdova",
        "phone": "930000000",
        "email": "johan@gmail.com",
        "status": "A",
        "statusDescription": "Activo",
        "registerDate": "21/08/2018",
        "unregisterDate": "12/12/19",
        "authentication": "string",
        "userRegistration": "e760001",
        "userModification": "e760001",
        "modificationDate": "12/05/2019"
      }
    ]
  },
  {
    "id": "39",
    "documentType": "2",
    "documentTypeDescription": "DNI",
    "documentNumber": "74427801",
    "pointSale": "MSC_TELECOMUNICACIONES_JUNIN",
    "pointSaleCode": "San Miguel",
    "names": "Timoteo",
    "motherLastName": "Mendez",
    "lastName": "Lopez",
    "phone": "920000000",
    "email": "timoteo@gmail.com",
    "status": "I",
    "statusDescription": "Inactivo",
    "registerDate": "2021-02-26T15:25:46.000-05:00",
    "unregisterDate": "12/12/19",
    "authentication": "string",
    "userRegistration": "e760001",
    "userModification": "e760001",
    "modificationDate": "01/02/2019",
    "employeeId": "DV23565",
    "records": [
      {
        "id": "39",
        "documentType": "2",
        "documentTypeDescription": "DNI",
        "documentNumber": "74427801",
        "pointSale": "MSC_TELECOMUNICACIONES_JUNIN",
        "pointSaleCode": "San Miguel",
        "names": "Timoteo",
        "motherLastName": "Mendez",
        "lastName": "Lopez",
        "phone": "920000000",
        "email": "timoteo@gmail.com",
        "status": "I",
        "statusDescription": "Inactivo",
        "registerDate": "2017-01-20T15:25:46.000-05:00",
        "unregisterDate": "2019-12-12T15:25:46.000-05:00",
        "authentication": "string",
        "userRegistration": "e760001",
        "userModification": "e760001",
        "modificationDate": "01/02/2019"
      },
      {
        "id": "39",
        "documentType": "2",
        "documentTypeDescription": "DNI",
        "documentNumber": "74427801",
        "pointSale": "MSC_TELECOMUNICACIONES_JUNIN",
        "pointSaleCode": "San Miguel",
        "names": "Timoteo",
        "motherLastName": "Mendez",
        "lastName": "Lopez",
        "phone": "920000000",
        "email": "timoteo@gmail.com",
        "status": "I",
        "statusDescription": "Inactivo",
        "registerDate": "2015-01-20T15:25:46.000-05:00",
        "unregisterDate": "2017-12-12T15:25:46.000-05:00",
        "authentication": "string",
        "userRegistration": "e760001",
        "userModification": "e760001",
        "modificationDate": "01/02/2019"
      }
    ]
  },
  {
    "id": "34",
    "documentType": "2",
    "documentTypeDescription": "DNI",
    "documentNumber": "74427808",
    "pointSale": "MSC_TELECOMUNICACIONES_PIURA",
    "pointSaleCode": "Angamos",
    "names": "Carlos",
    "motherLastName": "Rodriguéz",
    "lastName": "Rojas",
    "phone": "930000000",
    "email": "carlos@gmail.com",
    "status": "A",
    "statusDescription": "Activo",
    "registerDate": "01/10/2020",
    "unregisterDate": "12/12/19",
    "authentication": "string",
    "userRegistration": "e760001",
    "userModification": "e760001",
    "modificationDate": "15/06/2019",
    "employeeId": "DV23565",
    "records": [
      {
        "id": "34",
        "documentType": "2",
        "documentTypeDescription": "DNI",
        "documentNumber": "74427808",
        "pointSale": "MSC_TELECOMUNICACIONES_PIURA",
        "pointSaleCode": "Angamos",
        "names": "Carlos",
        "motherLastName": "Rodriguéz",
        "lastName": "Rojas",
        "phone": "930000000",
        "email": "carlos@gmail.com",
        "status": "A",
        "statusDescription": "Activo",
        "registerDate": "01/10/2020",
        "unregisterDate": "12/12/19",
        "authentication": "string",
        "userRegistration": "e760001",
        "userModification": "e760001",
        "modificationDate": "15/06/2019"
      },
      {
        "id": "34",
        "documentType": "2",
        "documentTypeDescription": "DNI",
        "documentNumber": "74427808",
        "pointSale": "MSC_TELECOMUNICACIONES_PIURA",
        "pointSaleCode": "Angamos",
        "names": "Carlos",
        "motherLastName": "Rodriguéz",
        "lastName": "Rojas",
        "phone": "930000000",
        "email": "carlos@gmail.com",
        "status": "A",
        "statusDescription": "Activo",
        "registerDate": "01/10/2020",
        "unregisterDate": "12/12/19",
        "authentication": "string",
        "userRegistration": "e760001",
        "userModification": "e760001",
        "modificationDate": "15/06/2019"
      }
    ]
  },
  {
    "id": "30",
    "documentType": "2",
    "documentTypeDescription": "DNI",
    "documentNumber": "74427803",
    "pointSale": "MSC_TELECOMUNICACIONES_PIURA",
    "pointSaleCode": "San Miguel",
    "names": "Jhon",
    "motherLastName": "Doe",
    "lastName": "Doe",
    "phone": "930000000",
    "email": "carlos@gmail.com",
    "status": "A",
    "statusDescription": "Activo",
    "registerDate": "01/10/2020",
    "unregisterDate": "12/12/19",
    "authentication": "string",
    "userRegistration": "e760001",
    "userModification": "e760001",
    "modificationDate": "15/06/2019",
    "employeeId": "DV23565",
    "records": [
      {
        "id": "30",
        "documentType": "2",
        "documentTypeDescription": "DNI",
        "documentNumber": "74427803",
        "pointSale": "MSC_TELECOMUNICACIONES_LORETO",
        "pointSaleCode": "San Miguel",
        "names": "Jhon",
        "motherLastName": "Doe",
        "lastName": "Doe",
        "phone": "930000000",
        "email": "carlos@gmail.com",
        "status": "A",
        "statusDescription": "Activo",
        "registerDate": "01/10/2020",
        "unregisterDate": "12/12/19",
        "authentication": "string",
        "userRegistration": "e760001",
        "userModification": "e760001",
        "modificationDate": "15/06/2019"
      },
      {
        "id": "30",
        "documentType": "2",
        "documentTypeDescription": "DNI",
        "documentNumber": "74427803",
        "pointSale": "MSC_TELECOMUNICACIONES_PIURA",
        "pointSaleCode": "San Miguel",
        "names": "Jhon",
        "motherLastName": "Doe",
        "lastName": "Doe",
        "phone": "930000000",
        "email": "carlos@gmail.com",
        "status": "A",
        "statusDescription": "Activo",
        "registerDate": "01/10/2020",
        "unregisterDate": "12/12/19",
        "authentication": "string",
        "userRegistration": "e760001",
        "userModification": "e760001",
        "modificationDate": "15/06/2019"
      }
    ]
  }
]
